MANIFEST.in
README.md
setup.py
GFSDownload.egg-info/PKG-INFO
GFSDownload.egg-info/SOURCES.txt
GFSDownload.egg-info/dependency_links.txt
GFSDownload.egg-info/requires.txt
GFSDownload.egg-info/top_level.txt
python/GFSDownload.py
python/utils.py