Metadata-Version: 1.1
Name: GFSDownload
Version: 0.0.2
Summary: A utility to download GFS meteo data 
Home-page: https://github.com/yoannMoreau/GFSDownload
Author: Yoann M
Author-email: yoann.moreau@gmail.com
License: CCO
Platform: Posix;
Classifier: Development Status :: 3 - Alpha
